pvlwebtools/__init__.py
pvlwebtools/mcp_server.py
pvlwebtools/py.typed
pvlwebtools/web_fetch.py
pvlwebtools/web_search.py
pvl_webtools-1.0.1.dist-info/METADATA
pvl_webtools-1.0.1.dist-info/WHEEL
pvl_webtools-1.0.1.dist-info/entry_points.txt
pvl_webtools-1.0.1.dist-info/RECORD
