Metadata-Version: 2.4
Name: pvl-webtools
Version: 1.0.1
Summary: Web search (SearXNG) and fetch tools with MCP server
Project-URL: Repository, https://github.com/pvliesdonk/pvl-webtools
Author: pvliesdonk
License: MIT
Keywords: markitdown,mcp,metasearch,searxng,trafilatura,webfetch,websearch
Classifier: Development Status :: 4 - Beta
Classifier: Intended Audience :: Developers
Classifier: License :: OSI Approved :: MIT License
Classifier: Programming Language :: Python :: 3
Classifier: Programming Language :: Python :: 3.10
Classifier: Programming Language :: Python :: 3.11
Classifier: Programming Language :: Python :: 3.12
Classifier: Topic :: Internet :: WWW/HTTP
Classifier: Topic :: Software Development :: Libraries :: Python Modules
Requires-Python: >=3.10
Requires-Dist: httpx>=0.27
Provides-Extra: all
Requires-Dist: fastmcp>=2.0; extra == 'all'
Requires-Dist: markitdown>=0.1; extra == 'all'
Requires-Dist: trafilatura>=1.6; extra == 'all'
Provides-Extra: dev
Requires-Dist: fastmcp>=2.0; extra == 'dev'
Requires-Dist: markitdown>=0.1; extra == 'dev'
Requires-Dist: mypy>=1.0; extra == 'dev'
Requires-Dist: pre-commit>=3.0; extra == 'dev'
Requires-Dist: pytest-asyncio>=0.21; extra == 'dev'
Requires-Dist: pytest-cov>=4.0; extra == 'dev'
Requires-Dist: pytest>=7.0; extra == 'dev'
Requires-Dist: python-semantic-release>=10.0; extra == 'dev'
Requires-Dist: ruff>=0.1; extra == 'dev'
Requires-Dist: trafilatura>=1.6; extra == 'dev'
Provides-Extra: docs
Requires-Dist: mkdocs-material>=9.0; extra == 'docs'
Requires-Dist: mkdocs>=1.5; extra == 'docs'
Requires-Dist: mkdocstrings[python]>=0.24; extra == 'docs'
Provides-Extra: extraction
Requires-Dist: trafilatura>=1.6; extra == 'extraction'
Provides-Extra: markdown
Requires-Dist: markitdown>=0.1; extra == 'markdown'
Provides-Extra: mcp
Requires-Dist: fastmcp>=2.0; extra == 'mcp'
